jiratools/__init__.py
jiratools/error_logger.py
jiratools/formatting.py
jiratools/jira.config.example
jiratools-2.1.0.dist-info/entry_points.txt
jiratools-2.1.0.dist-info/LICENSE
jiratools-2.1.0.dist-info/WHEEL
jiratools-2.1.0.dist-info/METADATA
jiratools-2.1.0.dist-info/RECORD
