Metadata-Version: 2.1
Name: jiratools
Version: 2.1.0
Summary: Simple helpers to interface to JIRA from an API or command line.
Home-page: https://github.com/jolly-good-toolbelt/jiratools/
License: MIT
Author: Brad Brown
Author-email: brad@bradsbrown.com
Requires-Python: >=3.6,<4.0
Classifier: License :: OSI Approved :: MIT License
Classifier: Programming Language :: Python :: 3
Classifier: Programming Language :: Python :: 3.6
Classifier: Programming Language :: Python :: 3.7
Classifier: Programming Language :: Python :: 3.8
Requires-Dist: jira (>=2.0,<3.0)
Project-URL: Documentation, https://jolly-good-toolbelt.github.io/jiratools/
Project-URL: Repository, https://github.com/jolly-good-toolbelt/jiratools/
